{
    "video_id": null,
    "publish_date": null,
    "video_title": null,
    "treetagger_output": [
        {
            "Token": "in",
            "Tag": "IN",
            "Lemma": "in"
        },
        {
            "Token": "the",
            "Tag": "DT",
            "Lemma": "the"
        },
        {
            "Token": "cold",
            "Tag": "JJ",
            "Lemma": "cold"
        },
        {
            "Token": "winter",
            "Tag": "NN",
            "Lemma": "winter"
        },
        {
            "Token": "rain",
            "Tag": "NN",
            "Lemma": "rain"
        },
        {
            "Token": "a",
            "Tag": "DT",
            "Lemma": "a"
        },
        {
            "Token": "picture",
            "Tag": "NN",
            "Lemma": "picture"
        },
        {
            "Token": "of",
            "Tag": "IN",
            "Lemma": "of"
        },
        {
            "Token": "misery",
            "Tag": "NN",
            "Lemma": "misery"
        },
        {
            "Token": "and",
            "Tag": "CC",
            "Lemma": "and"
        },
        {
            "Token": "death",
            "Tag": "NN",
            "Lemma": "death"
        },
        {
            "Token": "in",
            "Tag": "IN",
            "Lemma": "in"
        },
        {
            "Token": "Northern",
            "Tag": "NP",
            "Lemma": "Northern"
        },
        {
            "Token": "Gaza",
            "Tag": "NP",
            "Lemma": "Gaza"
        },
        {
            "Token": "it",
            "Tag": "PP",
            "Lemma": "it"
        },
        {
            "Token": "'",
            "Tag": "POS",
            "Lemma": "'"
        },
        {
            "Token": "s",
            "Tag": "NNS",
            "Lemma": "s"
        },
        {
            "Token": "the",
            "Tag": "DT",
            "Lemma": "the"
        },
        {
            "Token": "body",
            "Tag": "NN",
            "Lemma": "body"
        },
        {
            "Token": "of",
            "Tag": "IN",
            "Lemma": "of"
        },
        {
            "Token": "a",
            "Tag": "DT",
            "Lemma": "a"
        },
        {
            "Token": "girl",
            "Tag": "NN",
            "Lemma": "girl"
        },
        {
            "Token": "killed",
            "Tag": "VVN",
            "Lemma": "kill"
        },
        {
            "Token": "in",
            "Tag": "IN",
            "Lemma": "in"
        },
        {
            "Token": "an",
            "Tag": "DT",
            "Lemma": "an"
        },
        {
            "Token": "Israeli",
            "Tag": "JJ",
            "Lemma": "Israeli"
        },
        {
            "Token": "attack",
            "Tag": "NN",
            "Lemma": "attack"
        },
        {
            "Token": "on",
            "Tag": "IN",
            "Lemma": "on"
        },
        {
            "Token": "jabalia",
            "Tag": "NN",
            "Lemma": "jabalia"
        },
        {
            "Token": "she",
            "Tag": "PP",
            "Lemma": "she"
        },
        {
            "Token": "was",
            "Tag": "VBD",
            "Lemma": "be"
        },
        {
            "Token": "found",
            "Tag": "VVN",
            "Lemma": "find"
        },
        {
            "Token": "but",
            "Tag": "CC",
            "Lemma": "but"
        },
        {
            "Token": "there",
            "Tag": "EX",
            "Lemma": "there"
        },
        {
            "Token": "are",
            "Tag": "VBP",
            "Lemma": "be"
        },
        {
            "Token": "many",
            "Tag": "JJ",
            "Lemma": "many"
        },
        {
            "Token": "still",
            "Tag": "RB",
            "Lemma": "still"
        },
        {
            "Token": "trapped",
            "Tag": "VVN",
            "Lemma": "trap"
        },
        {
            "Token": "under",
            "Tag": "IN",
            "Lemma": "under"
        },
        {
            "Token": "the",
            "Tag": "DT",
            "Lemma": "the"
        },
        {
            "Token": "rubble",
            "Tag": "NN",
            "Lemma": "rubble"
        },
        {
            "Token": "in",
            "Tag": "IN",
            "Lemma": "in"
        },
        {
            "Token": "the",
            "Tag": "DT",
            "Lemma": "the"
        },
        {
            "Token": "rain",
            "Tag": "NN",
            "Lemma": "rain"
        },
        {
            "Token": "ambulances",
            "Tag": "NNS",
            "Lemma": "ambulance"
        },
        {
            "Token": "are",
            "Tag": "VBP",
            "Lemma": "be"
        },
        {
            "Token": "stuck",
            "Tag": "VVN",
            "Lemma": "stick"
        },
        {
            "Token": "on",
            "Tag": "IN",
            "Lemma": "on"
        },
        {
            "Token": "flooded",
            "Tag": "VVN",
            "Lemma": "flood"
        },
        {
            "Token": "streets",
            "Tag": "NNS",
            "Lemma": "street"
        },
        {
            "Token": "but",
            "Tag": "CC",
            "Lemma": "but"
        },
        {
            "Token": "rescue",
            "Tag": "NN",
            "Lemma": "rescue"
        },
        {
            "Token": "workers",
            "Tag": "NNS",
            "Lemma": "worker"
        },
        {
            "Token": "of",
            "Tag": "IN",
            "Lemma": "of"
        },
        {
            "Token": "Gaza",
            "Tag": "NP",
            "Lemma": "Gaza"
        },
        {
            "Token": "are",
            "Tag": "VBP",
            "Lemma": "be"
        },
        {
            "Token": "still",
            "Tag": "RB",
            "Lemma": "still"
        },
        {
            "Token": "carrying",
            "Tag": "VVG",
            "Lemma": "carry"
        },
        {
            "Token": "on",
            "Tag": "IN",
            "Lemma": "on"
        },
        {
            "Token": "Israel",
            "Tag": "NP",
            "Lemma": "Israel"
        },
        {
            "Token": "'",
            "Tag": "POS",
            "Lemma": "'"
        },
        {
            "Token": "s",
            "Tag": "JJ",
            "Lemma": "s"
        },
        {
            "Token": "total",
            "Tag": "JJ",
            "Lemma": "total"
        },
        {
            "Token": "blockade",
            "Tag": "NN",
            "Lemma": "blockade"
        },
        {
            "Token": "and",
            "Tag": "CC",
            "Lemma": "and"
        },
        {
            "Token": "attacks",
            "Tag": "NNS",
            "Lemma": "attack"
        },
        {
            "Token": "have",
            "Tag": "VHP",
            "Lemma": "have"
        },
        {
            "Token": "pulverized",
            "Tag": "VVN",
            "Lemma": "pulverize"
        },
        {
            "Token": "gaza",
            "Tag": "NP",
            "Lemma": "Gaza"
        },
        {
            "Token": "'",
            "Tag": "POS",
            "Lemma": "'"
        },
        {
            "Token": "s",
            "Tag": "NN",
            "Lemma": "S"
        },
        {
            "Token": "already",
            "Tag": "RB",
            "Lemma": "already"
        },
        {
            "Token": "broken",
            "Tag": "VVN",
            "Lemma": "break"
        },
        {
            "Token": "SE",
            "Tag": "FW",
            "Lemma": "se"
        },
        {
            "Token": "system",
            "Tag": "NN",
            "Lemma": "system"
        },
        {
            "Token": "and",
            "Tag": "CC",
            "Lemma": "and"
        },
        {
            "Token": "now",
            "Tag": "RB",
            "Lemma": "now"
        },
        {
            "Token": "the",
            "Tag": "DT",
            "Lemma": "the"
        },
        {
            "Token": "streets",
            "Tag": "NNS",
            "Lemma": "street"
        },
        {
            "Token": "are",
            "Tag": "VBP",
            "Lemma": "be"
        },
        {
            "Token": "churning",
            "Tag": "VVG",
            "Lemma": "churn"
        },
        {
            "Token": "the",
            "Tag": "DT",
            "Lemma": "the"
        },
        {
            "Token": "decay",
            "Tag": "NN",
            "Lemma": "decay"
        },
        {
            "Token": "of",
            "Tag": "IN",
            "Lemma": "of"
        },
        {
            "Token": "War",
            "Tag": "NP",
            "Lemma": "War"
        },
        {
            "Token": "these",
            "Tag": "DT",
            "Lemma": "these"
        },
        {
            "Token": "makeshift",
            "Tag": "NN",
            "Lemma": "makeshift"
        },
        {
            "Token": "tents",
            "Tag": "VVZ",
            "Lemma": "tent"
        },
        {
            "Token": "too",
            "Tag": "RB",
            "Lemma": "too"
        },
        {
            "Token": "offer",
            "Tag": "VV",
            "Lemma": "offer"
        },
        {
            "Token": "little",
            "Tag": "JJ",
            "Lemma": "little"
        },
        {
            "Token": "protection",
            "Tag": "NN",
            "Lemma": "protection"
        },
        {
            "Token": "for",
            "Tag": "IN",
            "Lemma": "for"
        },
        {
            "Token": "tens",
            "Tag": "NNS",
            "Lemma": "ten"
        },
        {
            "Token": "of",
            "Tag": "IN",
            "Lemma": "of"
        },
        {
            "Token": "thousands",
            "Tag": "NNS",
            "Lemma": "thousand"
        },
        {
            "Token": "of",
            "Tag": "IN",
            "Lemma": "of"
        },
        {
            "Token": "Palestinians",
            "Tag": "NPS",
            "Lemma": "Palestinians"
        },
        {
            "Token": "struggling",
            "Tag": "VVG",
            "Lemma": "struggle"
        },
        {
            "Token": "to",
            "Tag": "TO",
            "Lemma": "to"
        },
        {
            "Token": "stay",
            "Tag": "VV",
            "Lemma": "stay"
        },
        {
            "Token": "dry",
            "Tag": "JJ",
            "Lemma": "dry"
        },
        {
            "Token": "and",
            "Tag": "CC",
            "Lemma": "and"
        },
        {
            "Token": "warm",
            "Tag": "JJ",
            "Lemma": "warm"
        },
        {
            "Token": "we",
            "Tag": "PP",
            "Lemma": "we"
        },
        {
            "Token": "got",
            "Tag": "VVD",
            "Lemma": "get"
        },
        {
            "Token": "drenched",
            "Tag": "VVN",
            "Lemma": "drench"
        },
        {
            "Token": "inside",
            "Tag": "IN",
            "Lemma": "inside"
        },
        {
            "Token": "the",
            "Tag": "DT",
            "Lemma": "the"
        },
        {
            "Token": "tent",
            "Tag": "NN",
            "Lemma": "tent"
        },
        {
            "Token": "and",
            "Tag": "CC",
            "Lemma": "and"
        },
        {
            "Token": "I",
            "Tag": "PP",
            "Lemma": "I"
        },
        {
            "Token": "don",
            "Tag": "VVP",
            "Lemma": "don"
        },
        {
            "Token": "'",
            "Tag": "''",
            "Lemma": "'"
        },
        {
            "Token": "t",
            "Tag": "NN",
            "Lemma": "t"
        },
        {
            "Token": "know",
            "Tag": "VVP",
            "Lemma": "know"
        },
        {
            "Token": "where",
            "Tag": "WRB",
            "Lemma": "where"
        },
        {
            "Token": "to",
            "Tag": "TO",
            "Lemma": "to"
        },
        {
            "Token": "put",
            "Tag": "VV",
            "Lemma": "put"
        },
        {
            "Token": "the",
            "Tag": "DT",
            "Lemma": "the"
        },
        {
            "Token": "children",
            "Tag": "NNS",
            "Lemma": "child"
        },
        {
            "Token": "water",
            "Tag": "NN",
            "Lemma": "water"
        },
        {
            "Token": "flooded",
            "Tag": "VVD",
            "Lemma": "flood"
        },
        {
            "Token": "the",
            "Tag": "DT",
            "Lemma": "the"
        },
        {
            "Token": "tent",
            "Tag": "NN",
            "Lemma": "tent"
        },
        {
            "Token": "I",
            "Tag": "PP",
            "Lemma": "I"
        },
        {
            "Token": "wrapped",
            "Tag": "VVD",
            "Lemma": "wrap"
        },
        {
            "Token": "the",
            "Tag": "DT",
            "Lemma": "the"
        },
        {
            "Token": "children",
            "Tag": "NNS",
            "Lemma": "child"
        },
        {
            "Token": "in",
            "Tag": "IN",
            "Lemma": "in"
        },
        {
            "Token": "blankets",
            "Tag": "NNS",
            "Lemma": "blanket"
        },
        {
            "Token": "and",
            "Tag": "CC",
            "Lemma": "and"
        },
        {
            "Token": "came",
            "Tag": "VVD",
            "Lemma": "come"
        },
        {
            "Token": "here",
            "Tag": "RB",
            "Lemma": "here"
        },
        {
            "Token": "I",
            "Tag": "PP",
            "Lemma": "I"
        },
        {
            "Token": "don",
            "Tag": "VV",
            "Lemma": "don"
        },
        {
            "Token": "'",
            "Tag": "''",
            "Lemma": "'"
        },
        {
            "Token": "t",
            "Tag": "NN",
            "Lemma": "t"
        },
        {
            "Token": "know",
            "Tag": "VVP",
            "Lemma": "know"
        },
        {
            "Token": "what",
            "Tag": "WP",
            "Lemma": "what"
        },
        {
            "Token": "to",
            "Tag": "TO",
            "Lemma": "to"
        },
        {
            "Token": "do",
            "Tag": "VV",
            "Lemma": "do"
        },
        {
            "Token": "because",
            "Tag": "IN",
            "Lemma": "because"
        },
        {
            "Token": "of",
            "Tag": "IN",
            "Lemma": "of"
        },
        {
            "Token": "the",
            "Tag": "DT",
            "Lemma": "the"
        },
        {
            "Token": "rain",
            "Tag": "NN",
            "Lemma": "rain"
        },
        {
            "Token": "where",
            "Tag": "WRB",
            "Lemma": "where"
        },
        {
            "Token": "to",
            "Tag": "TO",
            "Lemma": "to"
        },
        {
            "Token": "go",
            "Tag": "VV",
            "Lemma": "go"
        },
        {
            "Token": "there",
            "Tag": "EX",
            "Lemma": "there"
        },
        {
            "Token": "is",
            "Tag": "VBZ",
            "Lemma": "be"
        },
        {
            "Token": "no",
            "Tag": "RB",
            "Lemma": "no"
        },
        {
            "Token": "no",
            "Tag": "DT",
            "Lemma": "no"
        },
        {
            "Token": "drinking",
            "Tag": "NN",
            "Lemma": "drinking"
        },
        {
            "Token": "water",
            "Tag": "NN",
            "Lemma": "water"
        },
        {
            "Token": "so",
            "Tag": "IN",
            "Lemma": "so"
        },
        {
            "Token": "families",
            "Tag": "NNS",
            "Lemma": "family"
        },
        {
            "Token": "are",
            "Tag": "VBP",
            "Lemma": "be"
        },
        {
            "Token": "collecting",
            "Tag": "VVG",
            "Lemma": "collect"
        },
        {
            "Token": "rain",
            "Tag": "NN",
            "Lemma": "rain"
        },
        {
            "Token": "water",
            "Tag": "NN",
            "Lemma": "water"
        },
        {
            "Token": "to",
            "Tag": "TO",
            "Lemma": "to"
        },
        {
            "Token": "drink",
            "Tag": "VV",
            "Lemma": "drink"
        },
        {
            "Token": "food",
            "Tag": "NN",
            "Lemma": "food"
        },
        {
            "Token": "medicine",
            "Tag": "NN",
            "Lemma": "medicine"
        },
        {
            "Token": "and",
            "Tag": "CC",
            "Lemma": "and"
        },
        {
            "Token": "fuel",
            "Tag": "NN",
            "Lemma": "fuel"
        },
        {
            "Token": "are",
            "Tag": "VBP",
            "Lemma": "be"
        },
        {
            "Token": "all",
            "Tag": "RB",
            "Lemma": "all"
        },
        {
            "Token": "running",
            "Tag": "VVG",
            "Lemma": "run"
        },
        {
            "Token": "low",
            "Tag": "JJ",
            "Lemma": "low"
        },
        {
            "Token": "for",
            "Tag": "IN",
            "Lemma": "for"
        },
        {
            "Token": "many",
            "Tag": "JJ",
            "Lemma": "many"
        },
        {
            "Token": "who",
            "Tag": "WP",
            "Lemma": "who"
        },
        {
            "Token": "had",
            "Tag": "VHD",
            "Lemma": "have"
        },
        {
            "Token": "to",
            "Tag": "TO",
            "Lemma": "to"
        },
        {
            "Token": "escape",
            "Tag": "VV",
            "Lemma": "escape"
        },
        {
            "Token": "Israel",
            "Tag": "NP",
            "Lemma": "Israel"
        },
        {
            "Token": "'",
            "Tag": "POS",
            "Lemma": "'"
        },
        {
            "Token": "s",
            "Tag": "JJ",
            "Lemma": "s"
        },
        {
            "Token": "Onslaught",
            "Tag": "NN",
            "Lemma": "onslaught"
        },
        {
            "Token": "with",
            "Tag": "IN",
            "Lemma": "with"
        },
        {
            "Token": "just",
            "Tag": "JJ",
            "Lemma": "just"
        },
        {
            "Token": "clothes",
            "Tag": "NNS",
            "Lemma": "clothes"
        },
        {
            "Token": "on",
            "Tag": "IN",
            "Lemma": "on"
        },
        {
            "Token": "their",
            "Tag": "PP$",
            "Lemma": "their"
        },
        {
            "Token": "backs",
            "Tag": "NNS",
            "Lemma": "back"
        },
        {
            "Token": "there",
            "Tag": "EX",
            "Lemma": "there"
        },
        {
            "Token": "are",
            "Tag": "VBP",
            "Lemma": "be"
        },
        {
            "Token": "no",
            "Tag": "DT",
            "Lemma": "no"
        },
        {
            "Token": "blankets",
            "Tag": "NNS",
            "Lemma": "blanket"
        },
        {
            "Token": "no",
            "Tag": "DT",
            "Lemma": "no"
        },
        {
            "Token": "mattresses",
            "Tag": "NNS",
            "Lemma": "mattress"
        },
        {
            "Token": "just",
            "Tag": "RB",
            "Lemma": "just"
        },
        {
            "Token": "the",
            "Tag": "DT",
            "Lemma": "the"
        },
        {
            "Token": "looming",
            "Tag": "VVG",
            "Lemma": "loom"
        },
        {
            "Token": "threat",
            "Tag": "NN",
            "Lemma": "threat"
        },
        {
            "Token": "of",
            "Tag": "IN",
            "Lemma": "of"
        },
        {
            "Token": "disease",
            "Tag": "NN",
            "Lemma": "disease"
        },
        {
            "Token": "and",
            "Tag": "CC",
            "Lemma": "and"
        },
        {
            "Token": "starvation",
            "Tag": "NN",
            "Lemma": "starvation"
        },
        {
            "Token": "what",
            "Tag": "WP",
            "Lemma": "what"
        },
        {
            "Token": "is",
            "Tag": "VBZ",
            "Lemma": "be"
        },
        {
            "Token": "the",
            "Tag": "DT",
            "Lemma": "the"
        },
        {
            "Token": "fault",
            "Tag": "NN",
            "Lemma": "fault"
        },
        {
            "Token": "of",
            "Tag": "IN",
            "Lemma": "of"
        },
        {
            "Token": "this",
            "Tag": "DT",
            "Lemma": "this"
        },
        {
            "Token": "child",
            "Tag": "NN",
            "Lemma": "child"
        },
        {
            "Token": "who",
            "Tag": "WP",
            "Lemma": "who"
        },
        {
            "Token": "was",
            "Tag": "VBD",
            "Lemma": "be"
        },
        {
            "Token": "born",
            "Tag": "VVN",
            "Lemma": "bear"
        },
        {
            "Token": "in",
            "Tag": "IN",
            "Lemma": "in"
        },
        {
            "Token": "a",
            "Tag": "DT",
            "Lemma": "a"
        },
        {
            "Token": "tent",
            "Tag": "NN",
            "Lemma": "tent"
        },
        {
            "Token": "in",
            "Tag": "IN",
            "Lemma": "in"
        },
        {
            "Token": "war",
            "Tag": "NN",
            "Lemma": "war"
        },
        {
            "Token": "there",
            "Tag": "EX",
            "Lemma": "there"
        },
        {
            "Token": "are",
            "Tag": "VBP",
            "Lemma": "be"
        },
        {
            "Token": "no",
            "Tag": "DT",
            "Lemma": "no"
        },
        {
            "Token": "clothes",
            "Tag": "NNS",
            "Lemma": "clothes"
        },
        {
            "Token": "for",
            "Tag": "IN",
            "Lemma": "for"
        },
        {
            "Token": "her",
            "Tag": "PP",
            "Lemma": "her"
        },
        {
            "Token": "no",
            "Tag": "DT",
            "Lemma": "no"
        },
        {
            "Token": "food",
            "Tag": "NN",
            "Lemma": "food"
        },
        {
            "Token": "or",
            "Tag": "CC",
            "Lemma": "or"
        },
        {
            "Token": "drink",
            "Tag": "VV",
            "Lemma": "drink"
        },
        {
            "Token": "the",
            "Tag": "DT",
            "Lemma": "the"
        },
        {
            "Token": "children",
            "Tag": "NNS",
            "Lemma": "child"
        },
        {
            "Token": "here",
            "Tag": "RB",
            "Lemma": "here"
        },
        {
            "Token": "cry",
            "Tag": "VVP",
            "Lemma": "cry"
        },
        {
            "Token": "for",
            "Tag": "IN",
            "Lemma": "for"
        },
        {
            "Token": "moral",
            "Tag": "JJ",
            "Lemma": "moral"
        },
        {
            "Token": "of",
            "Tag": "IN",
            "Lemma": "of"
        },
        {
            "Token": "bread",
            "Tag": "NN",
            "Lemma": "bread"
        },
        {
            "Token": "I",
            "Tag": "PP",
            "Lemma": "I"
        },
        {
            "Token": "appeal",
            "Tag": "VVP",
            "Lemma": "appeal"
        },
        {
            "Token": "to",
            "Tag": "TO",
            "Lemma": "to"
        },
        {
            "Token": "the",
            "Tag": "DT",
            "Lemma": "the"
        },
        {
            "Token": "world",
            "Tag": "NN",
            "Lemma": "world"
        },
        {
            "Token": "those",
            "Tag": "DT",
            "Lemma": "those"
        },
        {
            "Token": "who",
            "Tag": "WP",
            "Lemma": "who"
        },
        {
            "Token": "have",
            "Tag": "VHP",
            "Lemma": "have"
        },
        {
            "Token": "a",
            "Tag": "DT",
            "Lemma": "a"
        },
        {
            "Token": "conscience",
            "Tag": "NN",
            "Lemma": "conscience"
        },
        {
            "Token": "to",
            "Tag": "TO",
            "Lemma": "to"
        },
        {
            "Token": "save",
            "Tag": "VV",
            "Lemma": "save"
        },
        {
            "Token": "us",
            "Tag": "PP",
            "Lemma": "us"
        },
        {
            "Token": "from",
            "Tag": "IN",
            "Lemma": "from"
        },
        {
            "Token": "what",
            "Tag": "WP",
            "Lemma": "what"
        },
        {
            "Token": "we",
            "Tag": "PP",
            "Lemma": "we"
        },
        {
            "Token": "are",
            "Tag": "VBP",
            "Lemma": "be"
        },
        {
            "Token": "in",
            "Tag": "IN",
            "Lemma": "in"
        },
        {
            "Token": "and",
            "Tag": "CC",
            "Lemma": "and"
        },
        {
            "Token": "return",
            "Tag": "VV",
            "Lemma": "return"
        },
        {
            "Token": "to",
            "Tag": "TO",
            "Lemma": "to"
        },
        {
            "Token": "our",
            "Tag": "PP$",
            "Lemma": "our"
        },
        {
            "Token": "homes",
            "Tag": "NNS",
            "Lemma": "home"
        },
        {
            "Token": "Israel",
            "Tag": "NP",
            "Lemma": "Israel"
        },
        {
            "Token": "has",
            "Tag": "VHZ",
            "Lemma": "have"
        },
        {
            "Token": "ignored",
            "Tag": "VVN",
            "Lemma": "ignore"
        },
        {
            "Token": "calls",
            "Tag": "NNS",
            "Lemma": "call"
        },
        {
            "Token": "for",
            "Tag": "IN",
            "Lemma": "for"
        },
        {
            "Token": "a",
            "Tag": "DT",
            "Lemma": "a"
        },
        {
            "Token": "ceasefire",
            "Tag": "NN",
            "Lemma": "ceasefire"
        },
        {
            "Token": "with",
            "Tag": "IN",
            "Lemma": "with"
        },
        {
            "Token": "indication",
            "Tag": "NN",
            "Lemma": "indication"
        },
        {
            "Token": "that",
            "Tag": "IN/that",
            "Lemma": "that"
        },
        {
            "Token": "its",
            "Tag": "PP$",
            "Lemma": "its"
        },
        {
            "Token": "assault",
            "Tag": "NN",
            "Lemma": "assault"
        },
        {
            "Token": "on",
            "Tag": "IN",
            "Lemma": "on"
        },
        {
            "Token": "Gaza",
            "Tag": "NP",
            "Lemma": "Gaza"
        },
        {
            "Token": "could",
            "Tag": "MD",
            "Lemma": "could"
        },
        {
            "Token": "last",
            "Tag": "VV",
            "Lemma": "last"
        },
        {
            "Token": "for",
            "Tag": "IN",
            "Lemma": "for"
        },
        {
            "Token": "months",
            "Tag": "NNS",
            "Lemma": "month"
        },
        {
            "Token": "and",
            "Tag": "CC",
            "Lemma": "and"
        },
        {
            "Token": "so",
            "Tag": "RB",
            "Lemma": "so"
        },
        {
            "Token": "would",
            "Tag": "MD",
            "Lemma": "would"
        },
        {
            "Token": "the",
            "Tag": "DT",
            "Lemma": "the"
        },
        {
            "Token": "collective",
            "Tag": "JJ",
            "Lemma": "collective"
        },
        {
            "Token": "punishment",
            "Tag": "NN",
            "Lemma": "punishment"
        },
        {
            "Token": "of",
            "Tag": "IN",
            "Lemma": "of"
        },
        {
            "Token": "Palestinians",
            "Tag": "NPS",
            "Lemma": "Palestinians"
        },
        {
            "Token": "in",
            "Tag": "IN",
            "Lemma": "in"
        },
        {
            "Token": "this",
            "Tag": "DT",
            "Lemma": "this"
        },
        {
            "Token": "winter",
            "Tag": "NN",
            "Lemma": "winter"
        },
        {
            "Token": "of",
            "Tag": "IN",
            "Lemma": "of"
        },
        {
            "Token": "War",
            "Tag": "NP",
            "Lemma": "War"
        },
        {
            "Token": "make",
            "Tag": "VVP",
            "Lemma": "make"
        },
        {
            "Token": "sure",
            "Tag": "JJ",
            "Lemma": "sure"
        },
        {
            "Token": "to",
            "Tag": "TO",
            "Lemma": "to"
        },
        {
            "Token": "subscribe",
            "Tag": "VV",
            "Lemma": "subscribe"
        },
        {
            "Token": "to",
            "Tag": "TO",
            "Lemma": "to"
        },
        {
            "Token": "our",
            "Tag": "PP$",
            "Lemma": "our"
        },
        {
            "Token": "channel",
            "Tag": "NN",
            "Lemma": "channel"
        },
        {
            "Token": "to",
            "Tag": "TO",
            "Lemma": "to"
        },
        {
            "Token": "get",
            "Tag": "VV",
            "Lemma": "get"
        },
        {
            "Token": "the",
            "Tag": "DT",
            "Lemma": "the"
        },
        {
            "Token": "latest",
            "Tag": "JJS",
            "Lemma": "late"
        },
        {
            "Token": "news",
            "Tag": "NN",
            "Lemma": "news"
        },
        {
            "Token": "from",
            "Tag": "IN",
            "Lemma": "from"
        },
        {
            "Token": "Al",
            "Tag": "NP",
            "Lemma": "Al"
        }
    ]
}